tgre/__init__.py
tgre/tgre.py
tgre-1.0.dist-info/DESCRIPTION.rst
tgre-1.0.dist-info/METADATA
tgre-1.0.dist-info/RECORD
tgre-1.0.dist-info/WHEEL
tgre-1.0.dist-info/metadata.json
tgre-1.0.dist-info/top_level.txt
